skydroppy/__init__.py
skydroppy-0.1.3.dist-info/AUTHORS.rst
skydroppy-0.1.3.dist-info/LICENSE.txt
skydroppy-0.1.3.dist-info/METADATA
skydroppy-0.1.3.dist-info/WHEEL
skydroppy-0.1.3.dist-info/top_level.txt
skydroppy-0.1.3.dist-info/RECORD
