Metadata-Version: 2.1
Name: skydroppy
Version: 0.1.3
Summary: a python library for the Skydrop sprinkler controller API
Home-page: https://github.com/snicker/skydroppy/
Author: snicker
Author-email: ngordon779@gmail.com
License: mit
Platform: any
Classifier: Development Status :: 4 - Beta
Classifier: Programming Language :: Python
Requires-Dist: aiohttp
Provides-Extra: testing
Requires-Dist: pytest ; extra == 'testing'
Requires-Dist: pytest-cov ; extra == 'testing'
